build/lib/build/lib/jupyterlab_limit_output/__init__.py
build/lib/build/lib/jupyterlab_limit_output/_version.py
build/lib/jupyterlab_limit_output/__init__.py
build/lib/jupyterlab_limit_output/_version.py
build/lib/myvenv/bin/rst2html.py
build/lib/myvenv/bin/rst2html4.py
build/lib/myvenv/bin/rst2html5.py
build/lib/myvenv/bin/rst2latex.py
build/lib/myvenv/bin/rst2man.py
build/lib/myvenv/bin/rst2odt.py
build/lib/myvenv/bin/rst2odt_prepstyles.py
build/lib/myvenv/bin/rst2pseudoxml.py
build/lib/myvenv/bin/rst2s5.py
build/lib/myvenv/bin/rst2xetex.py
build/lib/myvenv/bin/rst2xml.py
build/lib/myvenv/bin/rstpep2html.py
jupyterlab_limit_output/__init__.py
jupyterlab_limit_output/_version.py
jupyterlab_limit_output/labextension/build_log.json
jupyterlab_limit_output/labextension/install.json
jupyterlab_limit_output/labextension/package.json
jupyterlab_limit_output/labextension/schemas/jupyterlab-limit-output/package.json.orig
jupyterlab_limit_output/labextension/schemas/jupyterlab-limit-output/settings.json
jupyterlab_limit_output/labextension/static/lib_index_js.088e5e2afd8e68ef3f50.js
jupyterlab_limit_output/labextension/static/lib_index_js.088e5e2afd8e68ef3f50.js.map
jupyterlab_limit_output/labextension/static/lib_index_js.8f7e72224f999b4227c6.js
jupyterlab_limit_output/labextension/static/lib_index_js.8f7e72224f999b4227c6.js.map
jupyterlab_limit_output/labextension/static/lib_index_js.ffe2091edae0050147bf.js
jupyterlab_limit_output/labextension/static/lib_index_js.ffe2091edae0050147bf.js.map
jupyterlab_limit_output/labextension/static/remoteEntry.03e3d8532caa3afb5cc7.js
jupyterlab_limit_output/labextension/static/remoteEntry.03e3d8532caa3afb5cc7.js.map
jupyterlab_limit_output/labextension/static/remoteEntry.bc9290952d30db774139.js
jupyterlab_limit_output/labextension/static/remoteEntry.bc9290952d30db774139.js.map
jupyterlab_limit_output/labextension/static/remoteEntry.d8030784757a1c70623e.js
jupyterlab_limit_output-2.0.0.dist-info/LICENSE.txt
jupyterlab_limit_output-2.0.0.dist-info/METADATA
jupyterlab_limit_output-2.0.0.dist-info/WHEEL
jupyterlab_limit_output-2.0.0.dist-info/top_level.txt
jupyterlab_limit_output-2.0.0.dist-info/RECORD
